UploadWrappers.py
KlWrappers-1.0.0.dist-info/METADATA
KlWrappers-1.0.0.dist-info/WHEEL
KlWrappers-1.0.0.dist-info/top_level.txt
KlWrappers-1.0.0.dist-info/RECORD
