Metadata-Version: 2.1
Name: KlWrappers
Version: 1.0.0
Summary: UNKNOWN
Home-page: UNKNOWN
Author: UNKNOWN
Author-email: UNKNOWN
License: UNKNOWN
Platform: UNKNOWN
Requires-Dist: paho-mqtt
Requires-Dist: kafka-python
